holidays/__init__.py
holidays/types.py
holiday_event_api-1.0.1.dist-info/LICENSE
holiday_event_api-1.0.1.dist-info/METADATA
holiday_event_api-1.0.1.dist-info/WHEEL
holiday_event_api-1.0.1.dist-info/top_level.txt
holiday_event_api-1.0.1.dist-info/RECORD
