Metadata-Version: 2.1
Name: holiday-event-api
Version: 1.0.1
Summary: The Official Holiday and Event API for Python
Home-page: https://github.com/westy92/holiday-event-api-python
Author: Seth Westphal
Author-email: seth@sethwestphal.com
Maintainer: Seth Westphal
License: MIT
Project-URL: Documentation, https://github.com/westy92/holiday-event-api-python
Project-URL: Releases, https://github.com/westy92/holiday-event-api-python/releases
Project-URL: Issues, https://github.com/westy92/holiday-event-api-python/issues
Project-URL: Funding, https://github.com/sponsors/westy92
Keywords: python,holiday,holidays,public,federal,official,unofficial,date,month,year,day,calendar,api,holidayapi,list,event,occurrence,celebration,description,details,checkiday,international,national,world,popular,trusted,accurate,free,best
Classifier: Development Status :: 5 - Production/Stable
Classifier: Development Status :: 6 - Mature
Classifier: Intended Audience :: Developers
Classifier: License :: OSI Approved :: MIT License
Classifier: Natural Language :: English
Classifier: Operating System :: OS Independent
Classifier: Programming Language :: Python :: 3.10
Classifier: Programming Language :: Python :: 3.11
Classifier: Programming Language :: Python :: 3.7
Classifier: Programming Language :: Python :: 3.8
Classifier: Programming Language :: Python :: 3.9
Classifier: Programming Language :: Python :: 3
Classifier: Programming Language :: Python :: Implementation :: PyPy
Classifier: Programming Language :: Python
Classifier: Topic :: Education
Classifier: Topic :: Internet :: WWW/HTTP :: Dynamic Content :: News/Diary
Classifier: Topic :: Software Development :: Libraries :: Python Modules
Classifier: Topic :: Utilities
Classifier: Typing :: Typed
Requires-Python: >=3.7, <4
License-File: LICENSE
Requires-Dist: requests (<3,>=2)
Requires-Dist: marshmallow-dataclass (>=8)
